{"cameraMode":{"drawMode":0,"name":"Shaded","section":"Shading Mode"},"sceneLighting":true,"audioPlay":false,"sceneViewState":{"m_AlwaysRefresh":false,"showFog":true,"showSkybox":true,"showFlares":true,"showImageEffects":true,"showParticleSystems":true,"showVisualEffectGraphs":true,"m_FxEnabled":true},"in2DMode":false,"pivot":{"x":-4.287965774536133,"y":10.440935134887696,"z":4.46754264831543},"rotation":{"x":0.1257675588130951,"y":-0.4199366569519043,"z":0.06876417249441147,"w":0.8973145484924316},"size":10.449999809265137,"orthographic":false}